{ "frames": [
   {
    "filename": "splash #splash 0.aseprite",
    "frame": { "x": 0, "y": 0, "w": 16, "h": 16 },
    "rotated": false,
    "trimmed": false,
    "spriteSourceSize": { "x": 0, "y": 0, "w": 16, "h": 16 },
    "sourceSize": { "w": 16, "h": 16 },
    "duration": 100
   },
   {
    "filename": "splash #splash 1.aseprite",
    "frame": { "x": 16, "y": 0, "w": 16, "h": 16 },
    "rotated": false,
    "trimmed": false,
    "spriteSourceSize": { "x": 0, "y": 0, "w": 16, "h": 16 },
    "sourceSize": { "w": 16, "h": 16 },
    "duration": 100
   }
 ],
 "meta": {
  "app": "http://www.aseprite.org/",
  "version": "1.2.16.3",
  "image": "splash.png",
  "format": "RGBA8888",
  "size": { "w": 32, "h": 16 },
  "scale": "1",
  "frameTags": [
   { "name": "splash", "from": 0, "to": 1, "direction": "forward" }
  ]
 }
}
