{
    "title": "Launcher",
    "developer": "Casual Effects",
    "copyright": "©2020-2023 Morgan McGuire",
    "license": "LGPL 3.0",
    "packages": [],
    "scripts": [],
    "start_mode": "$Play",
    "modes": [
        "_Play",
        "_SlideOut",
        "_Message"
    ],
    "assets": {
        "largeFont": "quad://fonts/deja-15.font.json",
        "mediumFont": "quad://fonts/deja-9.font.json",
        "smallFont": "quad://fonts/deja-7.font.json",
        "quadplayFont": "quad://fonts/weaver-10.font.json",
        "icons": "icons.sprite.json",
        "boop": "boop.sound.json",
        "pauseMessageSprite": "quad://console/os/pause-message.sprite.json"
    },
    "constants": {
        "textColor": {
            "type": "rgb",
            "value": {
                "r": {
                    "type": "number",
                    "value": 1
                },
                "g": {
                    "type": "number",
                    "value": 1
                },
                "b": {
                    "type": "number",
                    "value": 1
                }
            }
        }
    },
    "screenshot_tag": "Launcher",
    "description": "",
    "cooperative": false,
    "competitive": false,
    "highscores": false,
    "achievements": false,
    "min_players": 1,
    "max_players": 1
}
